setup.py
abcd_distributions/Binomialdistribution.py
abcd_distributions/Gaussiandistribution.py
abcd_distributions/Generaldistribution.py
abcd_distributions/__init__.py
abcd_distributions.egg-info/PKG-INFO
abcd_distributions.egg-info/SOURCES.txt
abcd_distributions.egg-info/dependency_links.txt
abcd_distributions.egg-info/not-zip-safe
abcd_distributions.egg-info/top_level.txt